mon_module/__init__.py
mon_module-0.0.1.dist-info/LICENSE
mon_module-0.0.1.dist-info/METADATA
mon_module-0.0.1.dist-info/WHEEL
mon_module-0.0.1.dist-info/top_level.txt
mon_module-0.0.1.dist-info/RECORD
